toncalculator/__init__.py
Toncalculator-0.0.4.dist-info/LICENCE.txt
Toncalculator-0.0.4.dist-info/METADATA
Toncalculator-0.0.4.dist-info/WHEEL
Toncalculator-0.0.4.dist-info/top_level.txt
Toncalculator-0.0.4.dist-info/RECORD
