Metadata-Version: 2.1
Name: Toncalculator
Version: 0.0.4
Summary: A basic scientific calculator
Home-page: UNKNOWN
Author: Mahmudul Hahan Tonmoy
Author-email: playerandgamertonmoy@gmail.com
License: MIT
Keywords: calculator toncalculator add addison subdivision log sin cos tan cat,sce cosec a simple calculator fine calculator terminal calculator
Platform: UNKNOWN
Classifier: Development Status :: 5 - Production/Stable
Classifier: Intended Audience :: Education
Classifier: Operating System :: OS Independent
Classifier: License :: OSI Approved :: MIT License
Classifier: Programming Language :: Python :: 3
